LICENSE.md
README.md
setup.cfg
setup.py
VidUniq/VideoUniquelizer.py
VidUniq/__init__.py
VidUniq/decorators.py
VidUniq/utils.py
VidUniq.egg-info/PKG-INFO
VidUniq.egg-info/SOURCES.txt
VidUniq.egg-info/dependency_links.txt
VidUniq.egg-info/requires.txt
VidUniq.egg-info/top_level.txt