Metadata-Version: 2.1
Name: VidUniq
Version: 2.0.0
Summary: A light video uniquelizer
Home-page: https://github.com/1floppa3/VidUniqLib
Download-URL: https://github.com/1floppa3/VidUniqLib/archive/main.zip
Author: 1Floppa3
Author-email: denis.kochetkov2006@gmail.com
License: GPL-3.0 license
Classifier: License :: OSI Approved :: GNU General Public License v3 (GPLv3)
Classifier: Operating System :: OS Independent
Classifier: Intended Audience :: End Users/Desktop
Classifier: Intended Audience :: Developers
Classifier: Programming Language :: Python
Classifier: Programming Language :: Python :: 3
Classifier: Programming Language :: Python :: 3 :: Only
Classifier: Programming Language :: Python :: 3.10
Classifier: Programming Language :: Python :: Implementation :: PyPy
Classifier: Programming Language :: Python :: Implementation :: CPython
Requires-Python: >=3.10
License-File: LICENSE.md
